hacking/__init__.py
hacking/config.py
hacking/core.py
hacking/checks/__init__.py
hacking/checks/comments.py
hacking/checks/dictlist.py
hacking/checks/docstrings.py
hacking/checks/except_checks.py
hacking/checks/imports.py
hacking/checks/localization.py
hacking/checks/mock_checks.py
hacking/checks/other.py
hacking/checks/vim_check.py
hacking/tests/__init__.py
hacking/tests/test_config.py
hacking/tests/test_doctest.py
hacking/tests/test_import_exceptions.py
hacking/tests/checks/__init__.py
hacking/tests/checks/test_comments.py
hacking/tests/checks/test_eventlet_imports.py
hacking/tests/checks/test_except_checks.py
hacking/tests/checks/test_mock.py
hacking/tests/checks/test_other.py
hacking-8.0.0.dist-info/AUTHORS
hacking-8.0.0.dist-info/LICENSE
hacking-8.0.0.dist-info/METADATA
hacking-8.0.0.dist-info/WHEEL
hacking-8.0.0.dist-info/entry_points.txt
hacking-8.0.0.dist-info/pbr.json
hacking-8.0.0.dist-info/top_level.txt
hacking-8.0.0.dist-info/RECORD
