Metadata-Version: 2.1
Name: hacking
Version: 8.0.0
Summary: OpenStack Hacking Guideline Enforcement
Home-page: https://docs.openstack.org/hacking/latest/
Author: OpenStack
Author-email: openstack-discuss@lists.openstack.org
Project-URL: Bug Tracker, https://bugs.launchpad.net/hacking
Project-URL: Reviews, https://review.opendev.org/q/p:openstack/hacking+status:open
Project-URL: CI, https://zuul.opendev.org/t/openstack/builds?project=openstack%2Fhacking
Project-URL: Source Code, https://opendev.org/openstack/hacking
Classifier: Development Status :: 4 - Beta
Classifier: Environment :: Console
Classifier: Environment :: OpenStack
Classifier: Intended Audience :: Developers
Classifier: Intended Audience :: Information Technology
Classifier: License :: OSI Approved :: Apache Software License
Classifier: Operating System :: OS Independent
Classifier: Programming Language :: Python
Classifier: Programming Language :: Python :: 3
Classifier: Programming Language :: Python :: 3.10
Classifier: Programming Language :: Python :: 3.11
Classifier: Programming Language :: Python :: 3.12
Classifier: Programming Language :: Python :: 3.13
Requires-Python: >=3.10
License-File: LICENSE
License-File: AUTHORS
Requires-Dist: flake8 ~=7.3.0
Provides-Extra: pep257
Requires-Dist: flake8-docstrings ==1.7.0 ; extra == 'pep257'
Provides-Extra: test
Requires-Dist: coverage !=4.4,>=4.0 ; extra == 'test'
Requires-Dist: fixtures >=3.0.0 ; extra == 'test'
Requires-Dist: python-subunit >=1.0.0 ; extra == 'test'
Requires-Dist: stestr >=2.0.0 ; extra == 'test'
Requires-Dist: testscenarios >=0.4 ; extra == 'test'
Requires-Dist: testtools >=2.2.0 ; extra == 'test'
Requires-Dist: ddt >=1.2.1 ; extra == 'test'
Requires-Dist: eventlet !=0.18.3,!=0.20.1,>=0.18.2 ; extra == 'test'
